{"name":"FreqSample","tagline":"A quick program to play frequencies.","body":"FreqSample\r\n==========\r\n\r\nFreqSample is a tool made in Java that will play a frequency.\r\n\r\n### Compiling\r\nMake sure you have the JDK installed along with Apache Ant. Then go to the root directory of this project and run:\r\n```\r\n$ ant jar\r\n```\r\n\r\n### Contributing\r\nSimply send in a pull request.\r\n\r\n### License\r\nThis program is licensed with the [GNU GPLv3](/LICENSE).\r\n","google":"","note":"Don't delete this file! It's used internally to help with page regeneration."}